pyc_dtypes_converter/LICENSE
pyc_dtypes_converter/README.MD
pyc_dtypes_converter/__init__.py
pyc_dtypes_converter/requirements.txt
pyc_dtypes_converter/thirdparty.json
pyc_dtypes_converter-0.10.dist-info/LICENSE.rst
pyc_dtypes_converter-0.10.dist-info/METADATA
pyc_dtypes_converter-0.10.dist-info/WHEEL
pyc_dtypes_converter-0.10.dist-info/top_level.txt
pyc_dtypes_converter-0.10.dist-info/RECORD
